tedata/__init__.py
tedata/__main__.py
tedata/base.py
tedata/check_highcharts.js
tedata/custom_datespan.js
tedata/firstLastDates.js
tedata/init_tooltips.js
tedata/latest_points.js
tedata/logger_setup.py
tedata/scrape_chart.py
tedata/scraper.py
tedata/search.py
tedata/utils.py
tedata-0.3.53.dist-info/METADATA
tedata-0.3.53.dist-info/WHEEL
tedata-0.3.53.dist-info/entry_points.txt
tedata-0.3.53.dist-info/RECORD
