Metadata-Version: 2.3
Name: tedata
Version: 0.3.53
Summary: Download data from Trading Economics for free and without any account or API key. Uses selenium, javascript & bs4 to scrape data. Trading Economics is one of the greatest stores of economic data on the web and contains millions of time-series for hundreds of different countries.
License: MIT
Author: the_macro_bootlegger
Requires-Python: >= 3.9
Classifier: License :: OSI Approved :: MIT License
Classifier: Programming Language :: Python :: 3
Classifier: Programming Language :: Python :: 3.9
Classifier: Programming Language :: Python :: 3.10
Classifier: Programming Language :: Python :: 3.11
Classifier: Programming Language :: Python :: 3.12
Classifier: Programming Language :: Python :: 3.13
Requires-Dist: beautifulsoup4 (>=4.12.3)
Requires-Dist: kaleido (>=0.2.0)
Requires-Dist: nbformat (>=4.2.0)
Requires-Dist: openpyxl (>=3.0.0)
Requires-Dist: pandas (>=2.2.1)
Requires-Dist: plotly (>=5.18.0)
Requires-Dist: selenium (>=4.27.1)
Project-URL: Bug Tracker, https://github.com/HelloThereMatey/tedata/issues
Project-URL: Firefox Download, https://www.mozilla.org/firefox/new/
Project-URL: Repository, https://github.com/HelloThereMatey/tedata
